mcp_serverless/__init__.py
mcp_serverless/core.py
mcp_serverless-0.1.0.dist-info/licenses/LICENSE
tests/__init__.py
tests/test_core.py
mcp_serverless-0.1.0.dist-info/METADATA
mcp_serverless-0.1.0.dist-info/WHEEL
mcp_serverless-0.1.0.dist-info/top_level.txt
mcp_serverless-0.1.0.dist-info/RECORD
